asyncudp/__init__.py
asyncudp/version.py
asyncudp-0.11.0.dist-info/LICENSE
asyncudp-0.11.0.dist-info/METADATA
asyncudp-0.11.0.dist-info/WHEEL
asyncudp-0.11.0.dist-info/top_level.txt
asyncudp-0.11.0.dist-info/RECORD
