Metadata-Version: 2.1
Name: asyncudp
Version: 0.11.0
Summary: Asyncio high level UDP sockets.
Home-page: https://github.com/eerimoq/asyncudp
Author: Erik Moqvist
Author-email: erik.moqvist@gmail.com
License: MIT
Keywords: asyncio
Classifier: License :: OSI Approved :: MIT License
Classifier: Programming Language :: Python :: 3
License-File: LICENSE
